paging.py
PagingServer-19.5.2.dist-info/LICENSE
PagingServer-19.5.2.dist-info/METADATA
PagingServer-19.5.2.dist-info/WHEEL
PagingServer-19.5.2.dist-info/entry_points.txt
PagingServer-19.5.2.dist-info/top_level.txt
PagingServer-19.5.2.dist-info/RECORD
