Metadata-Version: 2.1
Name: PagingServer
Version: 19.5.2
Summary: SIP-based Announcement / PA / Paging / Public Address Server system
Home-page: https://github.com/AccelerateNetworks/PagingServer
Author: Dan Ryan, Mike Kazantsev
Author-email: dan@seattlemesh.net, mk.fraggod@gmail.com
License: GPL-2
Keywords: sip,telephony,phone,paging,announcement,autoanswer,callpipe,klaxon,pj,pjproject,pjsip,pjsua,pulse,pulseaudio,pa
Platform: UNKNOWN
Classifier: Development Status :: 4 - Beta
Classifier: Environment :: No Input/Output (Daemon)
Classifier: Environment :: Other Environment
Classifier: Intended Audience :: Customer Service
Classifier: Intended Audience :: Telecommunications Industry
Classifier: License :: OSI Approved
Classifier: License :: OSI Approved :: GNU General Public License v2 (GPLv2)
Classifier: Natural Language :: English
Classifier: Operating System :: POSIX
Classifier: Operating System :: POSIX :: Linux
Classifier: Programming Language :: Python
Classifier: Programming Language :: Python :: 2.7
Classifier: Programming Language :: Python :: 2 :: Only
Classifier: Topic :: Communications :: Telephony
Classifier: Topic :: Multimedia :: Sound/Audio
Classifier: Topic :: Multimedia :: Sound/Audio :: Mixers
Classifier: Topic :: Multimedia :: Sound/Audio :: Speech
Requires-Dist: pulsectl
Provides-Extra: sentry
Requires-Dist: raven ; extra == 'sentry'
